{
  "bvh_list": [
    null,
    "backwards_rifle_walk",
    "hip_hop_dancing",
    "hurricane_kick",
    "strafing",
    "walking"
  ],
  "bvh_dir": "bvh",
  "bvh_skeleton_file": "bvh/name.json",
  "default_channel": "Zrotation",
  "default_scale": 10.0,
  "default_bias": 1500.0,
  "default_min": 500.0,
  "default_max": 2500.0,
  "default_speed_ms": 33,
  "default_servo_type": "bus",
  "axis_channel_map": {
    "roll": "Xrotation",
    "pitch": "Yrotation",
    "yaw": "Zrotation"
  },
  "servo_limits": {
    "1": {
      "min": 500,
      "max": 2500
    },
    "2": {
      "min": 500,
      "max": 2500
    },
    "3": {
      "min": 500,
      "max": 2500
    },
    "4": {
      "min": 500,
      "max": 2500
    },
    "5": {
      "min": 500,
      "max": 2500
    },
    "6": {
      "min": 500,
      "max": 2500
    },
    "7": {
      "min": 1500,
      "max": 2500
    },
    "8": {
      "min": 1500,
      "max": 2500
    },
    "9": {
      "min": 1167,
      "max": 1833
    },
    "10": {
      "min": 1167,
      "max": 1833
    },
    "11": {
      "min": 1167,
      "max": 1833
    },
    "12": {
      "min": 1167,
      "max": 1833
    },
    "13": {
      "min": 1167,
      "max": 1833
    },
    "14": {
      "min": 1167,
      "max": 1833
    }
  },
  "joint_alias": {
    "thigh.L": "hip.L",
    "thigh.R": "hip.R",
    "shin.L": "knee.L",
    "shin.R": "knee.R",
    "foot.L": "ankle.L",
    "foot.R": "ankle.R",
    "toe.L": "toe.L",
    "toe.R": "toe.R"
  },
  "joint_map": {
    "hip.R": {
      "right_hip_cube_joint_ctrl/right_hip_cube_joint": {
        "id": 1,
        "channel": "Yrotation",
        "scale": 15.0
      },
      "right_thigh_joint_ctrl/right_thigh_joint": {
        "id": 2,
        "channel": "Zrotation",
        "scale": 15.0
      },
      "right_hip_roll_joint_ctrl/right_hip_roll_joint": {
        "id": 6,
        "channel": "Xrotation",
        "scale": 15.0
      }
    },
    "knee.R": {
      "right_knee_joint_ctrl/right_knee_joint": {
        "id": 7,
        "channel": "Xrotation",
        "scale": 10.0,
        "bias": 2500.0,
        "min": 1500,
        "max": 2500
      }
    },
    "ankle.R": {
      "right_ankle_cube_joint_ctrl/right_ankle_cube_joint": "9",
      "right_ankle_axle_joint_ctrl/right_ankle_axle_joint": "10",
      "right_foot_joint_ctrl/right_foot_joint": "11",
      "9": "ankle.R.yaw",
      "10": "ankle.R.roll",
      "11": "ankle.R.pitch"
    },
    "toe.R": {
      "right_toe_joint_ctrl/right_toe_joint": "null"
    },
    "hip.L": {
      "left_hip_cube_joint_ctrl/left_hip_cube_joint": {
        "id": 3,
        "channel": "Yrotation",
        "scale": 15.0
      },
      "left_thigh_joint_ctrl/left_thigh_joint": {
        "id": 5,
        "channel": "Zrotation",
        "scale": 15.0
      },
      "left_hip_roll_joint_ctrl/left_hip_roll_joint": {
        "id": 4,
        "channel": "Xrotation",
        "scale": 15.0
      }
    },
    "knee.L": {
      "left_knee_joint_ctrl/left_knee_joint": {
        "id": 8,
        "channel": "Xrotation",
        "scale": 10.0,
        "bias": 2500.0,
        "min": 1500,
        "max": 2500
      }
    },
    "ankle.L": {
      "left_ankle_cube_joint_ctrl/left_ankle_cube_joint": "12",
      "left_ankle_axle_joint_ctrl/left_ankle_axle_joint": "13",
      "left_foot_joint_ctrl/left_foot_joint": "14",
      "12": "ankle.L.yaw",
      "13": "ankle.L.roll",
      "14": "ankle.L.pitch"
    },
    "toe.L": {
      "left_toe_joint_ctrl/left_toe_joint": "null"
    }
  },
  "bvh_action_files": {
    "backwards_rifle_walk.bvh": "backwards_rifle_walk.json",
    "hip_hop_dancing.bvh": "hip_hop_dancing.json",
    "hurricane_kick.bvh": "hurricane_kick.json",
    "strafing.bvh": "strafing.json",
    "walking.bvh": "walking.json"
  }
}
